{
  "schema": "world_edit_blueprint_lite",
  "version": 1,
  "id": "05_corner",
  "name": "Fort Corner",
  "created_at": "2026-04-04 00:00:00",
  "created_by": "system",
  "source": "curated_seed_pack_v1",
  "bounds": {
    "min_x": -2,
    "max_x": 0,
    "min_y": -2,
    "max_y": 0,
    "min_z": 0,
    "max_z": 0,
    "radius": 2
  },
  "entries": [
    {
      "type": "/obj/structure/barricade/metal/plasteel/wired",
      "dx": -2,
      "dy": -2,
      "dz": 0,
      "dir": 2,
      "vars": {}
    },
    {
      "type": "/obj/structure/barricade/metal/plasteel/wired",
      "dx": -1,
      "dy": -2,
      "dz": 0,
      "dir": 2,
      "vars": {}
    },
    {
      "type": "/obj/structure/barricade/metal/plasteel",
      "dx": 0,
      "dy": -2,
      "dz": 0,
      "dir": 2,
      "vars": {}
    },
    {
      "type": "/obj/structure/barricade/metal/plasteel",
      "dx": -2,
      "dy": -2,
      "dz": 0,
      "dir": 8,
      "vars": {}
    },
    {
      "type": "/obj/structure/barricade/metal/plasteel",
      "dx": -2,
      "dy": -1,
      "dz": 0,
      "dir": 8,
      "vars": {}
    },
    {
      "type": "/obj/structure/barricade/metal",
      "dx": -2,
      "dy": 0,
      "dz": 0,
      "dir": 8,
      "vars": {}
    },
    {
      "type": "/obj/structure/barricade/wooden",
      "dx": -1,
      "dy": 0,
      "dz": 0,
      "dir": 8,
      "vars": {}
    },
    {
      "type": "/obj/structure/barricade/metal",
      "dx": 0,
      "dy": 0,
      "dz": 0,
      "dir": 1,
      "vars": {}
    },
    {
      "type": "/obj/structure/barricade/wooden",
      "dx": -1,
      "dy": 0,
      "dz": 0,
      "dir": 1,
      "vars": {}
    }
  ]
}
